<?xml version="1.0" encoding="utf-8" ?>
<G20HPIs>
  <CountryStatistics>
    <Country>Argentina</Country>
    <Population>40412000</Population>
    <HPI>54.0550416711541</HPI>
    <Product>16011.6728032264</Product>
  </CountryStatistics>
  <CountryStatistics>
    <Country>Australia</Country>
    <Population>22299000</Population>
    <HPI>41.9798119494163</HPI>
    <Product>38159.6336533223</Product>
  </CountryStatistics>
  <CountryStatistics>
    <Country>Brazil</Country>
    <Population>194946000</Population>
    <HPI>52.9</HPI>
    <Product>11210.3908053823</Product>
  </CountryStatistics>
  <CountryStatistics>
    <Country>Canada</Country>
    <Population>34126000</Population>
    <HPI>43.5598389886338</HPI>
    <Product>39050.1673163719</Product>
  </CountryStatistics>
  <CountryStatistics>
    <Country>China</Country>
    <Population>1338300000</Population>
    <HPI>44.6607379337422</HPI>
    <Product>7599</Product>
  </CountryStatistics>
  <CountryStatistics>
    <Country>France</Country>
    <Population>64895000</Population>
    <HPI>46.5234761588933</HPI>
    <Product>34123.1966249035</Product>
  </CountryStatistics>
  <CountryStatistics>
    <Country>Germany</Country>
    <Population>81777000</Population>
    <HPI>47.2003845662555</HPI>
    <Product>37402.2677660974</Product>
  </CountryStatistics>
  <CountryStatistics>
    <Country>India</Country>
    <Population>1224615000</Population>
    <HPI>50.8654815019365</HPI>
    <Product>3425.4489267524</Product>
  </CountryStatistics>
  <CountryStatistics>
    <Country>Indonesia</Country>
    <Population>239870000</Population>
    <HPI>55.4818109066418</HPI>
    <Product>4325.2533282173</Product>
  </CountryStatistics>
  <CountryStatistics>
    <Country>Italy</Country>
    <Population>60483000</Population>
    <HPI>46.3519373312074</HPI>
    <Product>31954.1751781228</Product>
  </CountryStatistics>
  <CountryStatistics>
    <Country>Japan</Country>
    <Population>127451000</Population>
    <HPI>47.5081715147689</HPI>
    <Product>33732.8682226596</Product>
  </CountryStatistics>
  <CountryStatistics>
    <Country>Mexico</Country>
    <Population>113423000</Population>
    <HPI>52.8940295085293</HPI>
    <Product>14563.884253986</Product>
  </CountryStatistics>
  <CountryStatistics>
    <Country>Russia</Country>
    <Population>141750000</Population>
    <HPI>34.5182507109685</HPI>
    <Product>19891.3528339013</Product>
  </CountryStatistics>
  <CountryStatistics>
    <Country>Saudi Arabia</Country>
    <Population>27448000</Population>
    <HPI>45.9653828550535</HPI>
    <Product>22713.4852913284</Product>
  </CountryStatistics>
  <CountryStatistics>
    <Country>South Africa</Country>
    <Population>49991000</Population>
    <HPI>28.1901123587694</HPI>
    <Product>10565.1840563081</Product>
  </CountryStatistics>
  <CountryStatistics>
    <Country>South Korea</Country>
    <Population>48875000</Population>
    <HPI>43.780881607652</HPI>
    <Product>29101.0711400706</Product>
  </CountryStatistics>
  <CountryStatistics>
    <Country>Turkey</Country>
    <Population>72752000</Population>
    <HPI>47.6235435519035</HPI>
    <Product>15686.860167575</Product>
  </CountryStatistics>
  <CountryStatistics>
    <Country>United Kingdom</Country>
    <Population>62232000</Population>
    <HPI>47.925475723302</HPI>
    <Product>35686.1997705521</Product>
  </CountryStatistics>
  <CountryStatistics>
    <Country>Spain</Country>
    <Population>46071000</Population>
    <HPI>44.0627933559749</HPI>
    <Product>32230.3585974199</Product>
  </CountryStatistics>
  <CountryStatistics>
    <Country>USA</Country>
    <Population>309349000</Population>
    <HPI>37.3401060751431</HPI>
    <Product>47153.0094273427</Product>
  </CountryStatistics>
</G20HPIs>